aistore/__init__.py
aistore/client.py
aistore/common_requirements
aistore/version.py
aistore/botocore_patch/README.md
aistore/botocore_patch/__init__.py
aistore/botocore_patch/botocore.py
aistore/botocore_patch/botocore_requirements
aistore/pytorch/README.md
aistore/pytorch/__init__.py
aistore/pytorch/base_iter_dataset.py
aistore/pytorch/base_map_dataset.py
aistore/pytorch/batch_iter_dataset.py
aistore/pytorch/dev_requirements
aistore/pytorch/dynamic_sampler.py
aistore/pytorch/iter_dataset.py
aistore/pytorch/map_dataset.py
aistore/pytorch/multishard_dataset.py
aistore/pytorch/shard_reader.py
aistore/pytorch/utils.py
aistore/sdk/README.md
aistore/sdk/__init__.py
aistore/sdk/ais_source.py
aistore/sdk/archive_config.py
aistore/sdk/blob_download_config.py
aistore/sdk/bucket.py
aistore/sdk/client.py
aistore/sdk/cluster.py
aistore/sdk/const.py
aistore/sdk/enums.py
aistore/sdk/errors.py
aistore/sdk/job.py
aistore/sdk/list_object_flag.py
aistore/sdk/namespace.py
aistore/sdk/presence_poller.py
aistore/sdk/provider.py
aistore/sdk/request_client.py
aistore/sdk/response_handler.py
aistore/sdk/retry_config.py
aistore/sdk/retry_manager.py
aistore/sdk/session_manager.py
aistore/sdk/types.py
aistore/sdk/utils.py
aistore/sdk/wait_result.py
aistore/sdk/authn/README.md
aistore/sdk/authn/__init__.py
aistore/sdk/authn/access_attr.py
aistore/sdk/authn/authn_client.py
aistore/sdk/authn/cluster_manager.py
aistore/sdk/authn/errors.py
aistore/sdk/authn/response_handler.py
aistore/sdk/authn/role_manager.py
aistore/sdk/authn/token_manager.py
aistore/sdk/authn/types.py
aistore/sdk/authn/user_manager.py
aistore/sdk/batch/README.md
aistore/sdk/batch/__init__.py
aistore/sdk/batch/batch.py
aistore/sdk/batch/errors.py
aistore/sdk/batch/types.py
aistore/sdk/batch/extractor/__init__.py
aistore/sdk/batch/extractor/archive_stream_extractor.py
aistore/sdk/batch/extractor/extractor_manager.py
aistore/sdk/batch/extractor/tar_stream_extractor.py
aistore/sdk/batch/extractor/zip_stream_extractor.py
aistore-1.19.0.dist-info/METADATA
aistore-1.19.0.dist-info/WHEEL
aistore-1.19.0.dist-info/licenses/LICENSE
aistore-1.19.0.dist-info/RECORD
